localizationkit/__init__.py
localizationkit/configuration.py
localizationkit/exceptions.py
localizationkit/localization_types.py
localizationkit/tests/__init__.py
localizationkit/tests/comment_linebreaks.py
localizationkit/tests/comment_similarity.py
localizationkit/tests/duplicate_keys.py
localizationkit/tests/has_comments.py
localizationkit/tests/has_value.py
localizationkit/tests/invalid_tokens.py
localizationkit/tests/key_length.py
localizationkit/tests/objectivec_alternative_tokens.py
localizationkit/tests/placeholder_token_explanation.py
localizationkit/tests/swift_interpolation.py
localizationkit/tests/test_case.py
localizationkit/tests/token_adjacency.py
localizationkit/tests/token_matching.py
localizationkit/tests/token_position_identifiers.py
localizationkit/utility_types.py
localizationkit-3.1.0.dist-info/LICENSE
localizationkit-3.1.0.dist-info/METADATA
localizationkit-3.1.0.dist-info/WHEEL
localizationkit-3.1.0.dist-info/RECORD
