Metadata-Version: 2.1
Name: localizationkit
Version: 3.1.0
Summary: String localization tests
Home-page: https://github.com/Microsoft/localizationkit
License: MIT
Keywords: localization,strings,tests
Author: Dale Myers
Author-email: dalemy@microsoft.com
Requires-Python: >=3.11,<4.0
Classifier: Development Status :: 3 - Alpha
Classifier: Intended Audience :: Developers
Classifier: License :: OSI Approved :: MIT License
Classifier: Programming Language :: Python :: 3
Classifier: Programming Language :: Python :: 3.11
Classifier: Programming Language :: Python :: 3.12
Classifier: Programming Language :: Python :: 3.13
Classifier: Programming Language :: Python :: 3.10
Classifier: Programming Language :: Python :: 3.8
Classifier: Programming Language :: Python :: 3.9
Classifier: Topic :: Software Development
Classifier: Topic :: Software Development :: Testing
Classifier: Topic :: Utilities
Requires-Dist: toml (>=0.10.2,<0.11.0)
Project-URL: Repository, https://github.com/Microsoft/localizationkit
